{
  "pathToPandoc": "/opt/homebrew/bin/pandoc",
  "tooltipDelay": 400,
  "zoteroGroups": [
    {
      "id": 1,
      "name": "My Library",
      "lastUpdate": 1701892966267
    }
  ],
  "renderCitations": true,
  "renderCitationsReadingMode": true,
  "renderLinkCitations": true,
  "pullFromZotero": true,
  "cslStyleURL": "https://raw.githubusercontent.com/citation-style-language/styles/master/ieee-with-url.csl",
  "cslLang": "en-US",
  "hideLinks": true,
  "enableCiteKeyCompletion": true,
  "showCitekeyTooltips": true
}